besmarts/md.py
besmarts/mechanics/optimizers_openmm.py
besmarts_openmm-0.1.0.dist-info/METADATA
besmarts_openmm-0.1.0.dist-info/WHEEL
besmarts_openmm-0.1.0.dist-info/top_level.txt
besmarts_openmm-0.1.0.dist-info/RECORD
