Metadata-Version: 2.2
Name: besmarts-openmm
Version: 0.1.0
Summary: BESMARTS OpenMM plugin
Home-page: https://github.com/trevorgokey/besmarts
Author: Trevor Gokey
Author-email: tgokey@uci.edu
License: MIT
Classifier: Programming Language :: Python :: 3.6
Classifier: Programming Language :: Python :: 3.7
Classifier: Programming Language :: Python :: 3.8
Classifier: Programming Language :: Python :: 3.9
Classifier: Programming Language :: Python :: 3.10
Classifier: Programming Language :: Python :: 3.11
Classifier: Programming Language :: Python :: 3.12
Classifier: License :: OSI Approved :: MIT License
Classifier: Operating System :: OS Independent
Requires-Python: >=3.6
Requires-Dist: besmarts
Requires-Dist: besmarts-mechanics
Requires-Dist: openmm
Requires-Dist: numpy
Dynamic: author
Dynamic: author-email
Dynamic: classifier
Dynamic: description
Dynamic: description-content-type
Dynamic: home-page
Dynamic: license
Dynamic: requires-dist
Dynamic: requires-python
Dynamic: summary
